videosdk/plugins/azure/__init__.py
videosdk/plugins/azure/stt.py
videosdk/plugins/azure/tts.py
videosdk/plugins/azure/version.py
videosdk/plugins/azure/voice_live.py
videosdk_plugins_azure-0.0.58.dist-info/METADATA
videosdk_plugins_azure-0.0.58.dist-info/WHEEL
videosdk_plugins_azure-0.0.58.dist-info/RECORD
